<?xml version="1.0" encoding="utf-8"?>
<schemalist>

  <schema id="ar.xjuan.Cambalache"
          path="/ar/xjuan/Cambalache/"
          gettext-domain="cambalache">

    <key name='completed-intro' type='b'>
      <default>false</default>
    </key>

    <child name="state" schema="ar.xjuan.Cambalache.state"/>

  </schema>

  <schema id="ar.xjuan.Cambalache.state" path="/ar/xjuan/Cambalache/state/">
    <child name="window" schema="ar.xjuan.Cambalache.state.window"/>
  </schema>

  <schema id="ar.xjuan.Cambalache.state.window" path="/ar/xjuan/Cambalache/state/window/">
    <key name='state' type='u'>
      <default>0</default>
    </key>

    <key name='size' type='(ii)'>
      <default>(0,0)</default>
    </key>
  </schema>

</schemalist>
